.gitattributes
.gitignore
.travis.yml
CHANGELOG.rst
LICENSE.txt
MANIFEST
MANIFEST.in
README.rst
requirements.txt
requirements_dev.txt
setup.cfg
setup.py
tox.ini
httpsig/__init__.py
httpsig/requests_auth.py
httpsig/sign.py
httpsig/utils.py
httpsig/verify.py
httpsig/tests/__init__.py
httpsig/tests/rsa_private.pem
httpsig/tests/rsa_public.pem
httpsig/tests/test_signature.py
httpsig/tests/test_utils.py
httpsig/tests/test_verify.py
pyhttpsig.egg-info/PKG-INFO
pyhttpsig.egg-info/SOURCES.txt
pyhttpsig.egg-info/dependency_links.txt
pyhttpsig.egg-info/requires.txt
pyhttpsig.egg-info/top_level.txt
pyhttpsig.egg-info/zip-safe